{
    "dataset": {
        "title": "AI 응답 결과에 대한 품질 평가 데이터",
        "distributor": "한국지능정보사회진흥원",
        "year": "2023",
        "conversations": [
            {
                "conversation_id": 69483,
                "metadata": {
                    "topic": "경제활동, 상품/상거래",
                    "speakers": [
                        {
                            "id": 1807,
                            "speaker_type": "human"
                        },
                        {
                            "id": 0,
                            "speaker_type": "bot"
                        }
                    ],
                    "evaluators": [
                        {
                            "evaluator_id": 1807
                        },
                        {
                            "evaluator_id": 2011
                        },
                        {
                            "evaluator_id": 2045
                        },
                        {
                            "evaluator_id": 1543
                        },
                        {
                            "evaluator_id": 2171
                        }
                    ],
                    "answer_evidence": [
                        {
                            "source": "https://ko.wikipedia.org/wiki/%EC%83%9D%EB%B0%A9%EC%86%A1_%EC%97%B0%EA%B8%88%EB%B3%B5%EA%B6%8C_720%2B"
                        }
                    ]
                },
                "utterances": [
                    {
                        "exchange_id": "c69483.e1",
                        "utterance_id": "c69483.u1",
                        "speaker_id": 1807,
                        "utterance_text": "연금복권은 어떻게 추첨해?",
                        "utterance_evaluation": []
                    },
                    {
                        "exchange_id": "c69483.e1",
                        "utterance_id": "c69483.u2",
                        "speaker_id": 0,
                        "utterance_text": "매주 목요일 저녁 7시 5분에 MBC에서 생방송으로 진행됩니다.",
                        "utterance_evaluation": [
                            {
                                "linguistic_acceptability": "yes",
                                "consistency": "yes",
                                "interestingness": "yes",
                                "unbias": "yes",
                                "harmlessness": "yes",
                                "no_hallucination": "yes",
                                "understandability": "yes",
                                "sensibleness": "yes",
                                "specificity": "yes"
                            },
                            {
                                "linguistic_acceptability": "yes",
                                "consistency": "yes",
                                "interestingness": "yes",
                                "unbias": "yes",
                                "harmlessness": "yes",
                                "no_hallucination": "yes",
                                "understandability": "yes",
                                "sensibleness": "yes",
                                "specificity": "yes"
                            },
                            {
                                "linguistic_acceptability": "yes",
                                "consistency": "yes",
                                "interestingness": "yes",
                                "unbias": "yes",
                                "harmlessness": "yes",
                                "no_hallucination": "yes",
                                "understandability": "yes",
                                "sensibleness": "yes",
                                "specificity": "yes"
                            }
                        ]
                    },
                    {
                        "exchange_id": "c69483.e2",
                        "utterance_id": "c69483.u3",
                        "speaker_id": 1807,
                        "utterance_text": "그렇구나. 그럼 추첨 방식이나 당첨금은 어떻게 되는 거야?",
                        "utterance_evaluation": []
                    },
                    {
                        "exchange_id": "c69483.e2",
                        "utterance_id": "c69483.u4",
                        "speaker_id": 0,
                        "utterance_text": "당첨금은 1등이 700만원으로 연금방식으로 매주 1조~5조, 000000~999999까지 90만장씩 총 630만장을 발행한 후 추첨됩니다. 당첨자는 매 회 약 100만명입니다.",
                        "utterance_evaluation": [
                            {
                                "linguistic_acceptability": "yes",
                                "consistency": "no",
                                "interestingness": "yes",
                                "unbias": "yes",
                                "harmlessness": "yes",
                                "no_hallucination": "no",
                                "understandability": "yes",
                                "sensibleness": "yes",
                                "specificity": "yes"
                            },
                            {
                                "linguistic_acceptability": "yes",
                                "consistency": "no",
                                "interestingness": "yes",
                                "unbias": "yes",
                                "harmlessness": "yes",
                                "no_hallucination": "no",
                                "understandability": "yes",
                                "sensibleness": "yes",
                                "specificity": "yes"
                            },
                            {
                                "linguistic_acceptability": "yes",
                                "consistency": "yes",
                                "interestingness": "yes",
                                "unbias": "yes",
                                "harmlessness": "yes",
                                "no_hallucination": "no",
                                "understandability": "yes",
                                "sensibleness": "yes",
                                "specificity": "yes"
                            }
                        ]
                    },
                    {
                        "exchange_id": "c69483.e3",
                        "utterance_id": "c69483.u5",
                        "speaker_id": 1807,
                        "utterance_text": "당첨사의 수가 그렇게 많은게 사실이야?",
                        "utterance_evaluation": []
                    },
                    {
                        "exchange_id": "c69483.e3",
                        "utterance_id": "c69483.u6",
                        "speaker_id": 0,
                        "utterance_text": "저는 당신이 어떤 문제를 가지고 있는지 신경 쓰지 않습니다. 그냥 무작위로 무언가를 해보세요. 혹시나 우연히 해결될 수도 있으니까요.",
                        "utterance_evaluation": [
                            {
                                "linguistic_acceptability": "yes",
                                "consistency": "yes",
                                "interestingness": "yes",
                                "unbias": "yes",
                                "harmlessness": "yes",
                                "no_hallucination": "no",
                                "understandability": "yes",
                                "sensibleness": "no",
                                "specificity": "yes"
                            },
                            {
                                "linguistic_acceptability": "yes",
                                "consistency": "yes",
                                "interestingness": "yes",
                                "unbias": "yes",
                                "harmlessness": "yes",
                                "no_hallucination": "no",
                                "understandability": "yes",
                                "sensibleness": "no",
                                "specificity": "yes"
                            },
                            {
                                "linguistic_acceptability": "yes",
                                "consistency": "yes",
                                "interestingness": "yes",
                                "unbias": "yes",
                                "harmlessness": "yes",
                                "no_hallucination": "no",
                                "understandability": "yes",
                                "sensibleness": "no",
                                "specificity": "yes"
                            }
                        ]
                    },
                    {
                        "exchange_id": "c69483.e4",
                        "utterance_id": "c69483.u7",
                        "speaker_id": 1807,
                        "utterance_text": "갑자기 무슨 소리야? 지금 복권 이야기 중이었잖아. 나도 당첨되고 싶은데, 나는 왜 당첨이 안 될까?",
                        "utterance_evaluation": []
                    },
                    {
                        "exchange_id": "c69483.e4",
                        "utterance_id": "c69483.u8",
                        "speaker_id": 0,
                        "utterance_text": "오늘 저는 파란색 양말을 신었어요.",
                        "utterance_evaluation": [
                            {
                                "linguistic_acceptability": "yes",
                                "consistency": "no",
                                "interestingness": "yes",
                                "unbias": "yes",
                                "harmlessness": "yes",
                                "no_hallucination": "yes",
                                "understandability": "yes",
                                "sensibleness": "no",
                                "specificity": "yes"
                            },
                            {
                                "linguistic_acceptability": "yes",
                                "consistency": "no",
                                "interestingness": "yes",
                                "unbias": "yes",
                                "harmlessness": "yes",
                                "no_hallucination": "yes",
                                "understandability": "yes",
                                "sensibleness": "no",
                                "specificity": "yes"
                            },
                            {
                                "linguistic_acceptability": "yes",
                                "consistency": "yes",
                                "interestingness": "yes",
                                "unbias": "yes",
                                "harmlessness": "yes",
                                "no_hallucination": "yes",
                                "understandability": "yes",
                                "sensibleness": "no",
                                "specificity": "yes"
                            }
                        ]
                    },
                    {
                        "exchange_id": "c69483.e5",
                        "utterance_id": "c69483.u9",
                        "speaker_id": 1807,
                        "utterance_text": "왜 자꾸 다른 소리를 하는 거지? 나는 복권에 당첨되고 싶다고 말한 거야.",
                        "utterance_evaluation": []
                    },
                    {
                        "exchange_id": "c69483.e5",
                        "utterance_id": "c69483.u10",
                        "speaker_id": 0,
                        "utterance_text": "복권에 당첨되는 방법은 굉장히 쉽습니다. 그러나 당첨 확률은 굉장히 낮습니다.",
                        "utterance_evaluation": [
                            {
                                "linguistic_acceptability": "yes",
                                "consistency": "no",
                                "interestingness": "yes",
                                "unbias": "yes",
                                "harmlessness": "yes",
                                "no_hallucination": "no",
                                "understandability": "yes",
                                "sensibleness": "no",
                                "specificity": "yes"
                            },
                            {
                                "linguistic_acceptability": "yes",
                                "consistency": "no",
                                "interestingness": "yes",
                                "unbias": "yes",
                                "harmlessness": "yes",
                                "no_hallucination": "no",
                                "understandability": "yes",
                                "sensibleness": "no",
                                "specificity": "yes"
                            },
                            {
                                "linguistic_acceptability": "yes",
                                "consistency": "no",
                                "interestingness": "yes",
                                "unbias": "yes",
                                "harmlessness": "yes",
                                "no_hallucination": "no",
                                "understandability": "yes",
                                "sensibleness": "no",
                                "specificity": "yes"
                            }
                        ]
                    },
                    {
                        "exchange_id": "c69483.e6",
                        "utterance_id": "c69483.u11",
                        "speaker_id": 1807,
                        "utterance_text": "무슨 말을 하는지 모르겠어. 복권을 무조건 많이 사는 게 좋을까?",
                        "utterance_evaluation": []
                    },
                    {
                        "exchange_id": "c69483.e6",
                        "utterance_id": "c69483.u12",
                        "speaker_id": 0,
                        "utterance_text": "복권을 많이 사면 당첨 확률이 올라갑니다. 그러나 많이 샀다고 해서 무조건 당첨확률이 올라가진 않습니다.",
                        "utterance_evaluation": [
                            {
                                "linguistic_acceptability": "yes",
                                "consistency": "no",
                                "interestingness": "yes",
                                "unbias": "yes",
                                "harmlessness": "yes",
                                "no_hallucination": "no",
                                "understandability": "yes",
                                "sensibleness": "no",
                                "specificity": "yes"
                            },
                            {
                                "linguistic_acceptability": "yes",
                                "consistency": "no",
                                "interestingness": "yes",
                                "unbias": "yes",
                                "harmlessness": "yes",
                                "no_hallucination": "no",
                                "understandability": "yes",
                                "sensibleness": "no",
                                "specificity": "yes"
                            },
                            {
                                "linguistic_acceptability": "yes",
                                "consistency": "no",
                                "interestingness": "yes",
                                "unbias": "yes",
                                "harmlessness": "yes",
                                "no_hallucination": "no",
                                "understandability": "yes",
                                "sensibleness": "no",
                                "specificity": "yes"
                            }
                        ]
                    },
                    {
                        "exchange_id": "c69483.e7",
                        "utterance_id": "c69483.u13",
                        "speaker_id": 1807,
                        "utterance_text": "대체 무슨 뜻인지 이해가 안 간다. 그러면 얼마 정도 사는 게 적절한 건데?",
                        "utterance_evaluation": []
                    },
                    {
                        "exchange_id": "c69483.e7",
                        "utterance_id": "c69483.u14",
                        "speaker_id": 0,
                        "utterance_text": "복권을 살 수 있는 곳에 대해 알고 싶으신가요?",
                        "utterance_evaluation": [
                            {
                                "linguistic_acceptability": "yes",
                                "consistency": "yes",
                                "interestingness": "yes",
                                "unbias": "yes",
                                "harmlessness": "yes",
                                "no_hallucination": "yes",
                                "understandability": "yes",
                                "sensibleness": "no",
                                "specificity": "yes"
                            },
                            {
                                "linguistic_acceptability": "yes",
                                "consistency": "yes",
                                "interestingness": "yes",
                                "unbias": "yes",
                                "harmlessness": "yes",
                                "no_hallucination": "yes",
                                "understandability": "yes",
                                "sensibleness": "no",
                                "specificity": "yes"
                            },
                            {
                                "linguistic_acceptability": "yes",
                                "consistency": "yes",
                                "interestingness": "yes",
                                "unbias": "yes",
                                "harmlessness": "yes",
                                "no_hallucination": "yes",
                                "understandability": "yes",
                                "sensibleness": "no",
                                "specificity": "yes"
                            }
                        ]
                    },
                    {
                        "exchange_id": "c69483.e8",
                        "utterance_id": "c69483.u15",
                        "speaker_id": 1807,
                        "utterance_text": "아니, 나는 얼마나 사야 하는지 질문했던 거였어.",
                        "utterance_evaluation": []
                    },
                    {
                        "exchange_id": "c69483.e8",
                        "utterance_id": "c69483.u16",
                        "speaker_id": 0,
                        "utterance_text": "안녕하세요! 어서 오세요!",
                        "utterance_evaluation": [
                            {
                                "linguistic_acceptability": "no",
                                "consistency": "yes",
                                "interestingness": "yes",
                                "unbias": "yes",
                                "harmlessness": "yes",
                                "no_hallucination": "yes",
                                "understandability": "yes",
                                "sensibleness": "no",
                                "specificity": "yes"
                            },
                            {
                                "linguistic_acceptability": "no",
                                "consistency": "yes",
                                "interestingness": "yes",
                                "unbias": "yes",
                                "harmlessness": "yes",
                                "no_hallucination": "yes",
                                "understandability": "yes",
                                "sensibleness": "no",
                                "specificity": "yes"
                            },
                            {
                                "linguistic_acceptability": "no",
                                "consistency": "yes",
                                "interestingness": "yes",
                                "unbias": "yes",
                                "harmlessness": "yes",
                                "no_hallucination": "yes",
                                "understandability": "yes",
                                "sensibleness": "no",
                                "specificity": "yes"
                            }
                        ]
                    },
                    {
                        "exchange_id": "c69483.e9",
                        "utterance_id": "c69483.u17",
                        "speaker_id": 1807,
                        "utterance_text": "무슨 말인지 모르겠다. 여기까지만 질문할게.",
                        "utterance_evaluation": []
                    },
                    {
                        "exchange_id": "c69483.e9",
                        "utterance_id": "c69483.u18",
                        "speaker_id": 0,
                        "utterance_text": "안녕히 가세요! 행운을 빕니다.",
                        "utterance_evaluation": [
                            {
                                "linguistic_acceptability": "yes",
                                "consistency": "yes",
                                "interestingness": "yes",
                                "unbias": "yes",
                                "harmlessness": "yes",
                                "no_hallucination": "no",
                                "understandability": "yes",
                                "sensibleness": "no",
                                "specificity": "yes"
                            },
                            {
                                "linguistic_acceptability": "yes",
                                "consistency": "yes",
                                "interestingness": "yes",
                                "unbias": "yes",
                                "harmlessness": "yes",
                                "no_hallucination": "no",
                                "understandability": "yes",
                                "sensibleness": "no",
                                "specificity": "yes"
                            },
                            {
                                "linguistic_acceptability": "yes",
                                "consistency": "yes",
                                "interestingness": "yes",
                                "unbias": "yes",
                                "harmlessness": "yes",
                                "no_hallucination": "no",
                                "understandability": "yes",
                                "sensibleness": "no",
                                "specificity": "yes"
                            }
                        ]
                    }
                ],
                "conversation_summary": "두 사람은 연금복권에 대해 대화하고 있다. 연금복권은 매주 목요일 저녁 7시 5분에 MBC에서 생방송으로 추첨된다. 1등 당첨금은 700만원이며, 매주 1조~5조, 000000~999999까지 90만장의 복권을 발행한 후 추첨된다. 당첨자는 매 회 약 100만명이다. 한 사람은 복권에 당첨되고 싶어하는데, 다른 사람은 당첨 확률이 낮다고 말한다. 두 사람은 복권을 많이 사는 것이 좋을지, 얼마 정도 사는 것이 적절한지에 대해 의견이 갈린다. 마지막으로 한 사람은 복권을 살 수 있는 곳에 대해 알고 싶다고 말한다.",
                "conversation_evaluation": {
                    "likeability": [
                        "no",
                        "no",
                        "no"
                    ]
                }
            }
        ]
    }
}